tox_interpreters/__init__.py
tox_interpreters/hooks.py
tox_interpreters-0.1.0.dist-info/LICENSE
tox_interpreters-0.1.0.dist-info/METADATA
tox_interpreters-0.1.0.dist-info/WHEEL
tox_interpreters-0.1.0.dist-info/entry_points.txt
tox_interpreters-0.1.0.dist-info/top_level.txt
tox_interpreters-0.1.0.dist-info/RECORD
