Metadata-Version: 2.1
Name: tox-interpreters
Version: 0.1.0
Summary: Customize Python interpreters used to create tox testenvs
Home-page: https://github.com/sanjioh/tox-interpreters
Author: Fabio Sangiovanni
Author-email: sjh+github@sanjioh.org
License: MIT
Platform: UNKNOWN
Classifier: Development Status :: 3 - Alpha
Classifier: Framework :: tox
Classifier: Intended Audience :: Developers
Classifier: License :: OSI Approved :: MIT License
Classifier: Operating System :: OS Independent
Classifier: Programming Language :: Python
Classifier: Programming Language :: Python :: 3 :: Only
Classifier: Programming Language :: Python :: 3.5
Classifier: Programming Language :: Python :: 3.6
Classifier: Programming Language :: Python :: 3.7
Classifier: Programming Language :: Python :: 3.8
Classifier: Topic :: Software Development :: Testing
Requires-Dist: tox (<4.0.0,>=3.8.0)
